<?xml version="1.0" encoding="utf-8"?>
<Defs>
	<!-- ======================== Sonic ======================== -->
	<SoundDef>
		<defName>AArmoury_Sonic</defName>
		<context>MapOnly</context>
		<eventNames/>
		<subSounds>
			<li>
				<grains>
					<li Class="AudioGrain_Folder">
						<clipFolderPath>AArmoury_Sonic</clipFolderPath>
					</li>
				</grains>
				<pitchRange>
					<min>0.9770588</min>
					<max>1.137647</max>
				</pitchRange>
				<distRange>
					<min>0</min>
					<max>50.40025</max>
				</distRange>
				<sustainLoop>False</sustainLoop>
			</li>
		</subSounds>
	</SoundDef>
	<!-- ======================== Psychic ======================== -->
	<SoundDef>
		<defName>AArmoury_Psychic</defName>
		<context>MapOnly</context>
		<eventNames/>
		<subSounds>
			<li>
				<grains>
					<li Class="AudioGrain_Folder">
						<clipFolderPath>AArmoury_Psychic</clipFolderPath>
					</li>
				</grains>
				<pitchRange>
					<min>0.9770588</min>
					<max>1.137647</max>
				</pitchRange>
				<distRange>
					<min>0</min>
					<max>50.40025</max>
				</distRange>
				<sustainLoop>False</sustainLoop>
			</li>
		</subSounds>
	</SoundDef>
		<!-- ======================== Shatter ======================== -->
	<SoundDef>
		<defName>AArmoury_Shatter</defName>
		<context>MapOnly</context>
		<eventNames/>
		<subSounds>
			<li>
				<grains>
					<li Class="AudioGrain_Folder">
						<clipFolderPath>AArmoury_Shatter</clipFolderPath>
					</li>
				</grains>
				<pitchRange>
					<min>0.9770588</min>
					<max>1.137647</max>
				</pitchRange>
				<distRange>
					<min>0</min>
					<max>50.40025</max>
				</distRange>
				<sustainLoop>False</sustainLoop>
			</li>
		</subSounds>
	</SoundDef>
	<!-- ======================== Laser ======================== -->
	<SoundDef>
		<defName>AArmoury_Laser</defName>
		<context>MapOnly</context>
		<eventNames/>
		<subSounds>
			<li>
				<grains>
					<li Class="AudioGrain_Folder">
						<clipFolderPath>AArmoury_Laser</clipFolderPath>
					</li>
				</grains>
				<pitchRange>
					<min>0.9770588</min>
					<max>1.137647</max>
				</pitchRange>
				<distRange>
					<min>0</min>
					<max>50.40025</max>
				</distRange>
				<sustainLoop>False</sustainLoop>
			</li>
		</subSounds>
	</SoundDef>
	<!-- ======================== Gauss ======================== -->
	<SoundDef>
		<defName>AArmoury_Gauss</defName>
		<context>MapOnly</context>
		<eventNames/>
		<subSounds>
			<li>
				<grains>
					<li Class="AudioGrain_Folder">
						<clipFolderPath>AArmoury_Gauss</clipFolderPath>
					</li>
				</grains>
				<pitchRange>
					<min>0.9770588</min>
					<max>1.137647</max>
				</pitchRange>
				<distRange>
					<min>0</min>
					<max>50.40025</max>
				</distRange>
				<sustainLoop>False</sustainLoop>
			</li>
		</subSounds>
	</SoundDef>
	<!-- ======================== Rocket ======================== -->
	<SoundDef>
		<defName>AArmoury_Rocket</defName>
		<context>MapOnly</context>
		<eventNames/>
		<subSounds>
			<li>
				<grains>
					<li Class="AudioGrain_Folder">
						<clipFolderPath>AArmoury_Rocket</clipFolderPath>
					</li>
				</grains>
				<pitchRange>
					<min>0.9770588</min>
					<max>1.137647</max>
				</pitchRange>
				<distRange>
					<min>0</min>
					<max>50.40025</max>
				</distRange>
				<sustainLoop>False</sustainLoop>
			</li>
		</subSounds>
	</SoundDef>
	<!-- ======================== Vapor ======================== -->
	<SoundDef>
		<defName>AArmoury_Vapor</defName>
		<context>MapOnly</context>
		<eventNames/>
		<subSounds>
			<li>
				<grains>
					<li Class="AudioGrain_Folder">
						<clipFolderPath>AArmoury_Vapor</clipFolderPath>
					</li>
				</grains>
				<volumeRange>
					<min>40</min>
					<max>40</max>
				</volumeRange>
				<pitchRange>
					<min>0.9770588</min>
					<max>1.137647</max>
				</pitchRange>
				<distRange>
					<min>0</min>
					<max>50.40025</max>
				</distRange>
				<sustainLoop>False</sustainLoop>
			</li>
		</subSounds>
	</SoundDef>
	<!-- ======================== Dart ======================== -->
	<SoundDef>
		<defName>AArmoury_Dart</defName>
		<context>MapOnly</context>
		<eventNames/>
		<subSounds>
			<li>
				<grains>
					<li Class="AudioGrain_Folder">
						<clipFolderPath>AArmoury_Dart</clipFolderPath>
					</li>
				</grains>
				<pitchRange>
					<min>0.9770588</min>
					<max>1.137647</max>
				</pitchRange>
				<distRange>
					<min>0</min>
					<max>50.40025</max>
				</distRange>
				<sustainLoop>False</sustainLoop>
			</li>
		</subSounds>
	</SoundDef>
	<!-- ======================== Zap ======================== -->
	<SoundDef>
		<defName>AArmoury_Zap</defName>
		<context>MapOnly</context>
		<eventNames/>
		<subSounds>
			<li>
				<grains>
					<li Class="AudioGrain_Folder">
						<clipFolderPath>AArmoury_Zap</clipFolderPath>
					</li>
				</grains>
				<pitchRange>
					<min>0.9770588</min>
					<max>1.137647</max>
				</pitchRange>
				<distRange>
					<min>0</min>
					<max>50.40025</max>
				</distRange>
				<sustainLoop>False</sustainLoop>
			</li>
		</subSounds>
	</SoundDef>
	<!-- ======================== Acid ======================== -->
	<SoundDef>
		<defName>AArmoury_Acid</defName>
		<context>MapOnly</context>
		<eventNames/>
		<subSounds>
			<li>
				<grains>
					<li Class="AudioGrain_Folder">
						<clipFolderPath>AArmoury_Acid</clipFolderPath>
					</li>
				</grains>
				<pitchRange>
					<min>0.9770588</min>
					<max>1.137647</max>
				</pitchRange>
				<distRange>
					<min>0</min>
					<max>50.40025</max>
				</distRange>
				<sustainLoop>False</sustainLoop>
			</li>
		</subSounds>
	</SoundDef>
	
	<!-- ======================== Chainsaw ======================== -->
	<SoundDef>
		<defName>AArmoury_Chainsaw</defName>
		<context>MapOnly</context>
		<eventNames/>
		<subSounds>
			<li>
				<grains>
					<li Class="AudioGrain_Folder">
						<clipFolderPath>AArmoury_Chainsaw</clipFolderPath>
					</li>
				</grains>
				<pitchRange>
					<min>0.9770588</min>
					<max>1.137647</max>
				</pitchRange>
				<distRange>
					<min>0</min>
					<max>50.40025</max>
				</distRange>
				<sustainLoop>False</sustainLoop>
			</li>
		</subSounds>
	</SoundDef>
</Defs>